{
  "name": "r2k-consumer-staples",
  "description": "Russell 2000 Consumer Staples (60 companies)",
  "tickers": [
    "PSMT",
    "COCO",
    "CALM",
    "UNFI",
    "CHEF",
    "WDFC",
    "ANDE",
    "MZTI",
    "SPB",
    "TPB",
    "CENTA",
    "IPAR",
    "HLF",
    "UVV",
    "IMKTA",
    "FDP",
    "JJSF",
    "ENR",
    "DOLE",
    "SMPL",
    "WMK",
    "FIZZ",
    "ODC",
    "EPC",
    "TR",
    "GO",
    "SENEA",
    "JBSS",
    "AVO",
    "MAMA",
    "UTZ",
    "CVGW",
    "VLGEA",
    "NGVC",
    "NATR",
    "CENT",
    "BGS",
    "BYND",
    "NUS",
    "HNST",
    "WEST",
    "OLPX",
    "VITL",
    "MGPI",
    "ALCO",
    "LMNR",
    "NAGE",
    "USNA",
    "MED",
    "BRCC",
    "LWAY",
    "SKIN",
    "WALD",
    "HFFG",
    "HAIN",
    "ZVIA",
    "LFVN",
    "ISPR",
    "FTLF",
    "AFRI"
  ],
  "pairs": [
    [
      "PSMT",
      "COCO"
    ],
    [
      "CALM",
      "UNFI"
    ],
    [
      "CHEF",
      "WDFC"
    ],
    [
      "ANDE",
      "MZTI"
    ],
    [
      "SPB",
      "TPB"
    ],
    [
      "CENTA",
      "IPAR"
    ],
    [
      "HLF",
      "UVV"
    ],
    [
      "IMKTA",
      "FDP"
    ],
    [
      "JJSF",
      "ENR"
    ],
    [
      "DOLE",
      "SMPL"
    ],
    [
      "WMK",
      "FIZZ"
    ],
    [
      "ODC",
      "EPC"
    ],
    [
      "TR",
      "GO"
    ],
    [
      "SENEA",
      "JBSS"
    ],
    [
      "AVO",
      "MAMA"
    ],
    [
      "UTZ",
      "CVGW"
    ],
    [
      "VLGEA",
      "NGVC"
    ],
    [
      "NATR",
      "CENT"
    ],
    [
      "BGS",
      "BYND"
    ],
    [
      "NUS",
      "HNST"
    ],
    [
      "WEST",
      "OLPX"
    ],
    [
      "VITL",
      "MGPI"
    ],
    [
      "ALCO",
      "LMNR"
    ],
    [
      "NAGE",
      "USNA"
    ],
    [
      "MED",
      "BRCC"
    ],
    [
      "LWAY",
      "SKIN"
    ],
    [
      "WALD",
      "HFFG"
    ],
    [
      "HAIN",
      "ZVIA"
    ],
    [
      "LFVN",
      "ISPR"
    ],
    [
      "FTLF",
      "AFRI"
    ]
  ],
  "sector": "Consumer Staples",
  "vol_driver": "Russell 2000 Consumer Staples \u2014 small-cap sector fundamentals",
  "source": "iShares Russell 2000 ETF (IWM) holdings"
}